napari_bacseg/__init__.py
napari_bacseg/_widget.py
napari_bacseg/napari.yaml
napari_bacseg/GUI/__init__.py
napari_bacseg/GUI/gui.py
napari_bacseg/GUI/gui.ui
napari_bacseg/_tests/__init__.py
napari_bacseg/_tests/test_bacseg.py
napari_bacseg/_tests/test_widget.py
napari_bacseg/funcs/__init__.py
napari_bacseg/funcs/bactfit_utils.py
napari_bacseg/funcs/cell_events.py
napari_bacseg/funcs/cellpose_utils.py
napari_bacseg/funcs/colicoords_utils.py
napari_bacseg/funcs/databaseIO_utils.py
napari_bacseg/funcs/database_utils.py
napari_bacseg/funcs/events_utils.py
napari_bacseg/funcs/heatmap_utils.py
napari_bacseg/funcs/picasso_utils.py
napari_bacseg/funcs/refine_utils.py
napari_bacseg/funcs/statistics_utils.py
napari_bacseg/funcs/threading_utils.py
napari_bacseg/funcs/tiler_utils.py
napari_bacseg/funcs/undrift_utils.py
napari_bacseg/funcs/utils.py
napari_bacseg/funcs/widget_ui.py
napari_bacseg/funcs/IO/__init__.py
napari_bacseg/funcs/IO/export_utils.py
napari_bacseg/funcs/IO/imagej_utils.py
napari_bacseg/funcs/IO/import_utils.py
napari_bacseg/funcs/IO/json_utils.py
napari_bacseg/funcs/IO/olympus_utils.py
napari_bacseg/funcs/IO/oni_utils.py
napari_bacseg/funcs/IO/oufti_utils.py
napari_bacseg/funcs/IO/zeiss_utils.py
napari_bacseg-1.1.2.dist-info/LICENSE
napari_bacseg-1.1.2.dist-info/METADATA
napari_bacseg-1.1.2.dist-info/WHEEL
napari_bacseg-1.1.2.dist-info/entry_points.txt
napari_bacseg-1.1.2.dist-info/top_level.txt
napari_bacseg-1.1.2.dist-info/RECORD
