Metadata-Version: 2.1
Name: napari-bacseg
Version: 1.1.2
Summary: Bacterial segmentation and analysis platform than can inport/export files in multiple formats. Integrating many tools such as Cellpose, ColiCoords, Oufti/MicrobeTracker.
Author-email: Piers Turner <piers.turner@physics.ox.ac.uk>
Project-URL: Homepage, https://github.com/piedrro/napari-bacseg
Project-URL: Bug Tracker, https://github.com/piedrro/napari-bacseg/issues
Classifier: Framework :: napari
Classifier: Environment :: Plugins
Classifier: License :: OSI Approved :: BSD License
Classifier: Programming Language :: Python :: 3.9
Classifier: Operating System :: OS Independent
Requires-Python: >=3.9
License-File: LICENSE
Requires-Dist: napari[all]==0.5.0
Requires-Dist: torch
Requires-Dist: torchvision
Requires-Dist: cellpose==3.0.1
Requires-Dist: opencv-python
Requires-Dist: picassosr==0.7.3
Requires-Dist: bactfit>=0.1.6
Requires-Dist: numpy
Requires-Dist: pyqt5
Requires-Dist: pyqt6
Requires-Dist: qtpy
Requires-Dist: scipy
Requires-Dist: natsort
Requires-Dist: tqdm
Requires-Dist: imagecodecs
Requires-Dist: tifffile
Requires-Dist: pandas
Requires-Dist: mat4py
Requires-Dist: glob2
Requires-Dist: matplotlib
Requires-Dist: scikit-image
Requires-Dist: roifile
Requires-Dist: openpyxl
Requires-Dist: shapely
Requires-Dist: colicoords
Requires-Dist: psutil
Requires-Dist: xmltodict
Requires-Dist: astropy
Requires-Dist: tiler
Requires-Dist: imageio-ffmpeg
Requires-Dist: aicspylibczi
Requires-Dist: czifile
Requires-Dist: omnipose
Requires-Dist: h5py
Requires-Dist: pyqtgraph
Provides-Extra: testing
Requires-Dist: tox; extra == "testing"
Requires-Dist: pytest; extra == "testing"
Requires-Dist: pytest-cov; extra == "testing"
Requires-Dist: pytest-qt; extra == "testing"
Requires-Dist: napari; extra == "testing"
Requires-Dist: pyqt5; extra == "testing"
